llama_index/tools/finance/__init__.py
llama_index/tools/finance/base.py
llama_index/tools/finance/comparisons.py
llama_index/tools/finance/earnings.py
llama_index/tools/finance/news.py
llama_index/tools/finance/util.py
llama_index_tools_finance-0.4.1.dist-info/METADATA
llama_index_tools_finance-0.4.1.dist-info/WHEEL
llama_index_tools_finance-0.4.1.dist-info/licenses/LICENSE
llama_index_tools_finance-0.4.1.dist-info/RECORD
