Metadata-Version: 2.4
Name: llama-index-tools-finance
Version: 0.4.1
Summary: llama-index finance-tools integration
Author-email: Your Name <you@example.com>
License-Expression: MIT
License-File: LICENSE
Requires-Python: <3.12,>=3.9
Requires-Dist: llama-index-core<0.15,>=0.13.0
Requires-Dist: newsapi-python<0.3,>=0.2.7
Requires-Dist: pandas
Requires-Dist: pytrends<5,>=4.9.2
Requires-Dist: yfinance<0.3,>=0.2.36
